Metadata-Version: 1.0
Name: carrotColors
Version: 0.0.3
Summary: A carrot-themed color palette for python
Home-page: UNKNOWN
Author: Carrot-top Craig
Author-email: UNKNOWN
License: UNKNOWN
Platform: UNKNOWN
